{"url":"https:\/\/b24-qv1jr4.bitrix24.by\/rest\/entity.item.add.json","info":{"url":"https:\/\/b24-qv1jr4.bitrix24.by\/rest\/entity.item.add.json","content_type":"application\/json; charset=utf-8","http_code":200,"header_size":1206,"request_size":307,"filetime":-1,"ssl_verify_result":0,"redirect_count":0,"total_time":0.239376,"namelookup_time":0.004241,"connect_time":0.007209,"pretransfer_time":0.036438,"size_upload":113,"size_download":236,"speed_download":985,"speed_upload":472,"download_content_length":-1,"upload_content_length":113,"starttransfer_time":0.239323,"redirect_time":0,"redirect_url":"","primary_ip":"185.183.120.131","certinfo":[],"primary_port":443,"local_ip":"192.168.100.122","local_port":40560},"params":{"method":"entity.item.add","params":{"ENTITY":"adress","NAME":"Belarus","PROPERTY_VALUES":[],"SECTION":24,"auth":"cb14a262005bf19a005bdc1800000001000007c3ae7169e10007176dfb841897d67806"}},"result":{"result":2,"time":{"start":1654788698.4022,"finish":1654788698.5115,"duration":0.10928893089294,"processing":0.075634956359863,"date_start":"2022-06-09T18:31:38+03:00","date_finish":"2022-06-09T18:31:38+03:00","operating":0}}}